scanline_wrapper.py
scanline_python_wrapper-1.0.0.dist-info/LICENSE
scanline_python_wrapper-1.0.0.dist-info/METADATA
scanline_python_wrapper-1.0.0.dist-info/WHEEL
scanline_python_wrapper-1.0.0.dist-info/top_level.txt
scanline_python_wrapper-1.0.0.dist-info/RECORD
