Metadata-Version: 2.1
Name: scanline-python-wrapper
Version: 1.0.0
Summary: Python wrapper for the scanline CLI scanner tool for macOS
Author: Wanadev <contact@wanadev.fr>
License: BSD 3 Clause
License-File: LICENSE
Provides-Extra: dev
Requires-Dist: black ; extra == 'dev'
Requires-Dist: flake8 ; extra == 'dev'
Requires-Dist: nox ; extra == 'dev'
Requires-Dist: pytest ; extra == 'dev'
Requires-Dist: sphinx ; extra == 'dev'
Requires-Dist: sphinx-rtd-theme ; extra == 'dev'
